src/__init__.py
src/__main__.py
src/install.py
src/integrity.py
Mangrove-0.2.6.dist-info/LICENSE
Mangrove-0.2.6.dist-info/METADATA
Mangrove-0.2.6.dist-info/WHEEL
Mangrove-0.2.6.dist-info/top_level.txt
Mangrove-0.2.6.dist-info/RECORD
