Metadata-Version: 2.1
Name: Mangrove
Version: 0.2.6
Summary: A PostgreSQL extension manager
Home-page: https://atomgit.com/zouxiangneihe/Mangrove
Author: Haorong Xu
Author-email: db_haorong@outlook.com
Classifier: Programming Language :: Python :: 3
Classifier: License :: OSI Approved :: BSD License
Classifier: Operating System :: OS Independent
Requires-Python: >=3.6
License-File: LICENSE
Requires-Dist: argparse>=1.4.0
Requires-Dist: tabulate>=0.9.0
Requires-Dist: requests>=2.24.0
